setup.py
abao_matrix_operations/__init__.py
abao_matrix_operations/matrix_operations.py
abao_matrix_operations/test.py
abao_matrix_operations.egg-info/PKG-INFO
abao_matrix_operations.egg-info/SOURCES.txt
abao_matrix_operations.egg-info/dependency_links.txt
abao_matrix_operations.egg-info/not-zip-safe
abao_matrix_operations.egg-info/requires.txt
abao_matrix_operations.egg-info/top_level.txt