Metadata-Version: 1.0
Name: abao-matrix-operations
Version: 1.0
Summary: Basic Matrix Operations
Home-page: UNKNOWN
Author: Bilgehan Kılınç
Author-email: UNKNOWN
License: UNKNOWN
Platform: UNKNOWN
